tinyWinToast/__init__.py
tinyWinToast/tinyWinToast.py
tinywintoast-1.3.5.dist-info/LICENSE
tinywintoast-1.3.5.dist-info/METADATA
tinywintoast-1.3.5.dist-info/WHEEL
tinywintoast-1.3.5.dist-info/top_level.txt
tinywintoast-1.3.5.dist-info/RECORD
