Metadata-Version: 2.2
Name: tinyWinToast
Version: 1.3.5
Summary: Tiny Python library for displaying Windows toasts
Home-page: https://github.com/J-CITY/tinyWinToast
Author: J-CITY (Glushchenko Daniil)
License-File: LICENSE
Dynamic: author
Dynamic: description
Dynamic: home-page
Dynamic: summary
